{"paragraphs":[{"text":"\nvar defaultRDD = sc.textFile(\"wasb:///defaultfile.dat\")\nvar defaultRDDCount = defaultRDD.count()\nprint(defaultRDDCount)","dateUpdated":"2017-06-30T18:07:17+0000","config":{"colWidth":12,"graph":{"mode":"table","height":300,"optionOpen":false,"keys":[],"values":[],"groups":[],"scatter":{}},"enabled":true,"editorMode":"ace/mode/scala","editorHide":false,"tableHide":false},"settings":{"params":{},"forms":{}},"jobName":"paragraph_1498843697844_928142840","id":"20170630-172817_1464119525","result":{"code":"SUCCESS","type":"TEXT","msg":"\ndefaultRDD: org.apache.spark.rdd.RDD[String] = wasb:///defaultfile.dat MapPartitionsRDD[11] at textFile at <console>:27\ndefaultRDDCount: Long = 101\n101\n\n"},"dateCreated":"2017-06-30T17:28:17+0000","dateStarted":"2017-06-30T18:07:17+0000","dateFinished":"2017-06-30T18:07:21+0000","status":"FINISHED","progressUpdateIntervalMs":500,"$$hashKey":"object:690","focus":true},{"text":"var nondefaultRDD = sc.textFile(\"wasb://nondefault@negoelsparkzeppelinstore.blob.core.windows.net/nondefaultfile.dat\")\nvar nondefaultRDDCount = nondefaultRDD.count()\nprint(nondefaultRDDCount)","dateUpdated":"2017-06-30T17:43:33+0000","config":{"colWidth":12,"graph":{"mode":"table","height":300,"optionOpen":false,"keys":[],"values":[],"groups":[],"scatter":{}},"enabled":true,"editorMode":"ace/mode/scala","tableHide":false},"settings":{"params":{},"forms":{}},"jobName":"paragraph_1498843870151_353741736","id":"20170630-173110_980830971","result":{"code":"SUCCESS","type":"TEXT","msg":"nondefaultRDD: org.apache.spark.rdd.RDD[String] = wasb://nondefault@negoelsparkzeppelinstore.blob.core.windows.net/nondefaultfile.dat MapPartitionsRDD[3] at textFile at <console>:27\nnondefaultRDDCount: Long = 63\n63\n\n"},"dateCreated":"2017-06-30T17:31:10+0000","dateStarted":"2017-06-30T17:43:24+0000","dateFinished":"2017-06-30T17:43:28+0000","status":"FINISHED","progressUpdateIntervalMs":500,"$$hashKey":"object:691","focus":true},{"config":{"colWidth":12,"graph":{"mode":"table","height":300,"optionOpen":false,"keys":[],"values":[],"groups":[],"scatter":{}},"enabled":true,"editorMode":"ace/mode/scala"},"settings":{"params":{},"forms":{}},"jobName":"paragraph_1498843967270_-1142207960","id":"20170630-173247_605590430","dateCreated":"2017-06-30T17:32:47+0000","status":"FINISHED","progressUpdateIntervalMs":500,"$$hashKey":"object:692","dateUpdated":"2017-06-30T18:13:48+0000","dateFinished":"2017-06-30T18:13:54+0000","dateStarted":"2017-06-30T18:13:48+0000","result":{"code":"SUCCESS","type":"TEXT","msg":"\ndlRDD: org.apache.spark.rdd.RDD[String] = adl://negoelsparkzeppelindl.azuredatalakestore.net/datalakefile.dat MapPartitionsRDD[16] at textFile at <console>:27\ndlRDDCount: Long = 40\n40\n\n"},"text":"\n\nvar dlRDD = sc.textFile(\"adl://negoelsparkzeppelindl.azuredatalakestore.net/datalakefile.dat\")\nvar dlRDDCount = dlRDD.count()\nprint(dlRDDCount)","focus":true},{"config":{"colWidth":12,"graph":{"mode":"table","height":300,"optionOpen":false,"keys":[],"values":[],"groups":[],"scatter":{}},"enabled":true,"editorMode":"ace/mode/scala"},"settings":{"params":{},"forms":{}},"jobName":"paragraph_1498844671728_-1153558315","id":"20170630-174431_230625836","dateCreated":"2017-06-30T17:44:31+0000","status":"FINISHED","progressUpdateIntervalMs":500,"focus":true,"$$hashKey":"object:1104","dateUpdated":"2017-06-30T18:11:21+0000","dateFinished":"2017-06-30T18:11:28+0000","dateStarted":"2017-06-30T18:11:21+0000","result":{"code":"SUCCESS","type":"TEXT","msg":"\n\n"},"text":"dlRDD.saveAsTextFile(\"adl://negoelsparkzeppelindl.azuredatalakestore.net/datalakefile_otput.dat\")"},{"config":{"colWidth":12,"graph":{"mode":"table","height":300,"optionOpen":false,"keys":[],"values":[],"groups":[],"scatter":{}},"enabled":true,"editorMode":"ace/mode/scala"},"settings":{"params":{},"forms":{}},"jobName":"paragraph_1498846281471_18485882","id":"20170630-181121_633783852","dateCreated":"2017-06-30T18:11:21+0000","status":"FINISHED","progressUpdateIntervalMs":500,"focus":true,"$$hashKey":"object:1209","dateUpdated":"2017-06-30T18:15:47+0000","dateFinished":"2017-06-30T18:15:52+0000","dateStarted":"2017-06-30T18:15:47+0000","result":{"code":"SUCCESS","type":"TEXT","msg":"dlRDDOutput: org.apache.spark.rdd.RDD[String] = adl://negoelsparkzeppelindl.azuredatalakestore.net/datalakefile_otput.dat MapPartitionsRDD[20] at textFile at <console>:27\nres17: Long = 40\n\n"},"text":"var dlRDDOutput = sc.textFile(\"adl://negoelsparkzeppelindl.azuredatalakestore.net/datalakefile_otput.dat\")\ndlRDDOutput.count()"},{"config":{"colWidth":12,"graph":{"mode":"table","height":300,"optionOpen":false,"keys":[],"values":[],"groups":[],"scatter":{}},"enabled":true},"settings":{"params":{},"forms":{}},"jobName":"paragraph_1498846441231_2129431242","id":"20170630-181401_571361613","dateCreated":"2017-06-30T18:14:01+0000","status":"READY","progressUpdateIntervalMs":500,"focus":true,"$$hashKey":"object:1375"}],"name":"zeppelindemo","id":"2CN5EQSMS","angularObjects":{"2CPQ9UA3W:shared_process":[],"2CK878JRJ:shared_process":[],"2CMJXQTGZ:shared_process":[]},"config":{"looknfeel":"default"},"info":{}}